README.rst
setup.py
mlploy/__init__.py
mlploy/api_client.py
mlploy/config.py
mlploy/mlploy.py
mlploy/version.py
mlploy.egg-info/PKG-INFO
mlploy.egg-info/SOURCES.txt
mlploy.egg-info/dependency_links.txt
mlploy.egg-info/top_level.txt