Metadata-Version: 1.2
Name: mlploy
Version: 0.0.2
Summary: Machine Learning Inference with SQL
Home-page: https://www.mlploy.com
Author: Michele Dallachiesa
Author-email: michele.dallachiesa@mlploy.com
License: MIT
Platform: UNKNOWN
Classifier: Development Status :: 3 - Alpha
Classifier: Intended Audience :: Developers
Classifier: Intended Audience :: Science/Research
Classifier: Intended Audience :: System Administrators
Classifier: License :: OSI Approved :: MIT License
Classifier: Programming Language :: Python :: 3
Requires-Python: >=3.6
